aco/__init__.py
aco/cli/__init__.py
aco/cli/aco_config.py
aco/cli/aco_launch.py
aco/cli/aco_server.py
aco/common/__init__.py
aco/common/config.py
aco/common/constants.py
aco/common/logger.py
aco/common/utils.py
aco/runner/__init__.py
aco/runner/bird_utils.py
aco/runner/context_manager.py
aco/runner/develop_shim.py
aco/runner/fstring_rewriter.py
aco/runner/launch_scripts.py
aco/runner/patch_constants.py
aco/runner/patching_import_hook.py
aco/runner/taint_wrappers.py
aco/runner/monkey_patching/__init__.py
aco/runner/monkey_patching/_dev_patch.py
aco/runner/monkey_patching/_dev_patch_utils.py
aco/runner/monkey_patching/api_parser.py
aco/runner/monkey_patching/apply_monkey_patches.py
aco/runner/monkey_patching/patching_utils.py
aco/runner/monkey_patching/patches/__init__.py
aco/runner/monkey_patching/patches/anthropic_patches.py
aco/runner/monkey_patching/patches/builtin_patches.py
aco/runner/monkey_patching/patches/file_patches.py
aco/runner/monkey_patching/patches/langchain_patches.py
aco/runner/monkey_patching/patches/openai_patches.py
aco/runner/monkey_patching/patches/together_patches.py
aco/runner/monkey_patching/patches/uuid_patches.py
aco/runner/monkey_patching/patches/vertexai_patches.py
aco/server/__init__.py
aco/server/cache_manager.py
aco/server/db.py
aco/server/develop_server.py
aco/server/edit_manager.py
aco/server/telemetry/__init__.py
aco/server/telemetry/client.py
aco/server/telemetry/server_logger.py
aco/server/telemetry/snapshots.py
agops_bird-0.0.5.dist-info/METADATA
agops_bird-0.0.5.dist-info/WHEEL
agops_bird-0.0.5.dist-info/entry_points.txt
agops_bird-0.0.5.dist-info/top_level.txt
agops_bird-0.0.5.dist-info/RECORD
