Metadata-Version: 2.4
Name: agops-bird
Version: 0.0.5
Summary: A development tool for LLM call visualization and debugging
License-Expression: GPL-3.0-or-later
Requires-Python: >=3.10
Requires-Dist: pyyaml
Requires-Dist: dill
Requires-Dist: forbiddenfruit
Requires-Dist: supabase
Provides-Extra: dev
Requires-Dist: black==25.1.0; extra == "dev"
Requires-Dist: pytest; extra == "dev"
Requires-Dist: pre-commit; extra == "dev"
Requires-Dist: responses; extra == "dev"
Requires-Dist: openai; extra == "dev"
Requires-Dist: anthropic; extra == "dev"
Requires-Dist: openai-agents; extra == "dev"
Requires-Dist: google-genai; extra == "dev"
Provides-Extra: examples
Requires-Dist: openai; extra == "examples"
Requires-Dist: anthropic; extra == "examples"
Requires-Dist: openai-agents; extra == "examples"
Requires-Dist: google-genai; extra == "examples"
